{
  "base": "/wom/tjl/",
  "intro": "/wom/intro/",
  "title": "The Jeshua Letters",
  "bid": "tjl",
  "page": [
    {
      "fid": "tjl/",
      "title": "About The Jeshua Letters",
      "url": "/wom/intro/tjl/",
      "idx": 0,
      "next": "/wom/tjl/ack/",
      "prev": "/wom/tjl/epilogue/"
    },
    {
      "fid": "ack/",
      "title": "Acknowledgements",
      "complete": {
        "format": 1,
        "index": 0,
        "fb": 0
      },
      "url": "/wom/tjl/ack/",
      "idx": 1,
      "next": "/wom/tjl/foreword/",
      "prev": "/wom/intro/tjl/"
    },
    {
      "fid": "foreword/",
      "title": "Foreword",
      "complete": {
        "format": 1,
        "index": 0,
        "fb": 0
      },
      "url": "/wom/tjl/foreword/",
      "idx": 2,
      "next": "/wom/tjl/preface/",
      "prev": "/wom/tjl/ack/"
    },
    {
      "fid": "preface/",
      "title": "Preface",
      "complete": {
        "format": 1,
        "index": 0,
        "fb": 0
      },
      "url": "/wom/tjl/preface/",
      "idx": 3,
      "next": "/wom/tjl/chap01/",
      "prev": "/wom/tjl/foreword/"
    },
    {
      "fid": "chap01/",
      "title": "Chapter One",
      "complete": {
        "format": 1,
        "index": 0,
        "fb": 0
      },
      "url": "/wom/tjl/chap01/",
      "idx": 4,
      "next": "/wom/tjl/chap02/",
      "prev": "/wom/tjl/preface/"
    },
    {
      "fid": "chap02/",
      "title": "Chapter Two",
      "complete": {
        "format": 1,
        "index": 0,
        "fb": 0
      },
      "url": "/wom/tjl/chap02/",
      "idx": 5,
      "next": "/wom/tjl/chap03/",
      "prev": "/wom/tjl/chap01/"
    },
    {
      "fid": "chap03/",
      "title": "Chapter Three",
      "complete": {
        "format": 1,
        "index": 0,
        "fb": 0
      },
      "url": "/wom/tjl/chap03/",
      "idx": 6,
      "next": "/wom/tjl/chap04/",
      "prev": "/wom/tjl/chap02/"
    },
    {
      "fid": "chap04/",
      "title": "Chapter Four",
      "complete": {
        "format": 1,
        "index": 0,
        "fb": 0
      },
      "url": "/wom/tjl/chap04/",
      "idx": 7,
      "next": "/wom/tjl/chap05/",
      "prev": "/wom/tjl/chap03/"
    },
    {
      "fid": "chap05/",
      "title": "Chapter Five",
      "complete": {
        "format": 1,
        "index": 0,
        "fb": 0
      },
      "url": "/wom/tjl/chap05/",
      "idx": 8,
      "next": "/wom/tjl/chap06/",
      "prev": "/wom/tjl/chap04/"
    },
    {
      "fid": "chap06/",
      "title": "Chapter Six",
      "complete": {
        "format": 1,
        "index": 0,
        "fb": 0
      },
      "url": "/wom/tjl/chap06/",
      "idx": 9,
      "next": "/wom/tjl/chap07/",
      "prev": "/wom/tjl/chap05/"
    },
    {
      "fid": "chap07/",
      "title": "Chapter Seven",
      "complete": {
        "format": 1,
        "index": 0,
        "fb": 0
      },
      "url": "/wom/tjl/chap07/",
      "idx": 10,
      "next": "/wom/tjl/chap08/",
      "prev": "/wom/tjl/chap06/"
    },
    {
      "fid": "chap08/",
      "title": "Chapter Eight",
      "complete": {
        "format": 1,
        "index": 0,
        "fb": 0
      },
      "url": "/wom/tjl/chap08/",
      "idx": 11,
      "next": "/wom/tjl/chap09/",
      "prev": "/wom/tjl/chap07/"
    },
    {
      "fid": "chap09/",
      "title": "Chapter Nine",
      "complete": {
        "format": 1,
        "index": 0,
        "fb": 0
      },
      "url": "/wom/tjl/chap09/",
      "idx": 12,
      "next": "/wom/tjl/chap10/",
      "prev": "/wom/tjl/chap08/"
    },
    {
      "fid": "chap10/",
      "title": "Chapter Ten",
      "complete": {
        "format": 1,
        "index": 0,
        "fb": 0
      },
      "url": "/wom/tjl/chap10/",
      "idx": 13,
      "next": "/wom/tjl/chap11/",
      "prev": "/wom/tjl/chap09/"
    },
    {
      "fid": "chap11/",
      "title": "Chapter Eleven",
      "complete": {
        "format": 1,
        "index": 0,
        "fb": 0
      },
      "url": "/wom/tjl/chap11/",
      "idx": 14,
      "next": "/wom/tjl/chap12/",
      "prev": "/wom/tjl/chap10/"
    },
    {
      "fid": "chap12/",
      "title": "Chapter Tweleve",
      "complete": {
        "format": 1,
        "index": 0,
        "fb": 0
      },
      "url": "/wom/tjl/chap12/",
      "idx": 15,
      "next": "/wom/tjl/epilogue/",
      "prev": "/wom/tjl/chap11/"
    },
    {
      "fid": "epilogue/",
      "title": "Epilogue",
      "complete": {
        "format": 1,
        "index": 0,
        "fb": 0
      },
      "url": "/wom/tjl/epilogue/",
      "idx": 16,
      "next": "/wom/intro/tjl/",
      "prev": "/wom/tjl/chap12/"
    }
  ]
}
